pf_package_template/__init__.py
pf_package_template/flow.dag.yaml
pf_package_template/tools/__init__.py
pf_package_template/tools/my_tool.py
pf_package_template/yamls/my_tool.yaml
pf_package_template-0.0.9.dist-info/METADATA
pf_package_template-0.0.9.dist-info/WHEEL
pf_package_template-0.0.9.dist-info/entry_points.txt
pf_package_template-0.0.9.dist-info/top_level.txt
pf_package_template-0.0.9.dist-info/RECORD
