Metadata-Version: 2.1
Name: pf-package-template
Version: 0.0.9
Summary: This is the prompt flow package template
